{
  "train": {
    "n_events": 379372,
    "pct_events": 74.1,
    "n_vessels": 12871,
    "n_snapshots": 210,
    "total_edges": 289816,
    "encounter_edges": 36807,
    "colocation_edges": 253009,
    "label_distribution": {
      "hard_iuu": 0.171,
      "normal": 0.265,
      "probable_iuu": 0.072,
      "suspicious": 0.492
    },
    "flag_distribution": {
      "domestic": 0.493,
      "foreign": 0.507
    },
    "event_type_distribution": {
      "encounter": 0.097,
      "fishing": 0.493,
      "loitering": 0.305,
      "port_visit": 0.105
    }
  },
  "val": {
    "n_events": 57838,
    "pct_events": 11.3,
    "n_vessels": 4459,
    "n_snapshots": 26,
    "total_edges": 39005,
    "encounter_edges": 3578,
    "colocation_edges": 35427,
    "label_distribution": {
      "hard_iuu": 0.231,
      "normal": 0.286,
      "probable_iuu": 0.149,
      "suspicious": 0.334
    },
    "flag_distribution": {
      "domestic": 0.393,
      "foreign": 0.607
    },
    "event_type_distribution": {
      "encounter": 0.062,
      "fishing": 0.648,
      "loitering": 0.2,
      "port_visit": 0.091
    }
  },
  "test": {
    "n_events": 74762,
    "pct_events": 14.6,
    "n_vessels": 1457,
    "n_snapshots": 42,
    "total_edges": 49382,
    "encounter_edges": 5854,
    "colocation_edges": 43528,
    "label_distribution": {
      "hard_iuu": 0.309,
      "normal": 0.29,
      "probable_iuu": 0.183,
      "suspicious": 0.218
    },
    "flag_distribution": {
      "domestic": 0.418,
      "foreign": 0.582
    },
    "event_type_distribution": {
      "encounter": 0.078,
      "fishing": 0.811,
      "port_visit": 0.111
    }
  }
}